qtile_extras/__init__.py
qtile_extras/bar.py
qtile_extras/hook.py
qtile_extras/images.py
qtile_extras/py.typed
qtile_extras/layout/__init__.py
qtile_extras/layout/_mods.py
qtile_extras/layout/plasma.py
qtile_extras/layout/decorations/__init__.py
qtile_extras/layout/decorations/borders.py
qtile_extras/layout/decorations/injections.py
qtile_extras/layout/decorations/injections_wayland.py
qtile_extras/popup/__init__.py
qtile_extras/popup/menu.py
qtile_extras/popup/toolkit.py
qtile_extras/popup/templates/__init__.py
qtile_extras/popup/templates/mpris2.py
qtile_extras/popup/templates/volume.py
qtile_extras/resources/__init__.py
qtile_extras/resources/dbusmenu/__init__.py
qtile_extras/resources/dbusmenu/dbusmenu.py
qtile_extras/resources/footballscores/__init__.py
qtile_extras/resources/footballscores/exceptions.py
qtile_extras/resources/footballscores/footballmatch.py
qtile_extras/resources/footballscores/league.py
qtile_extras/resources/footballscores/matchdict.py
qtile_extras/resources/footballscores/matchevent.py
qtile_extras/resources/footballscores/morphlinks.py
qtile_extras/resources/footballscores/playeraction.py
qtile_extras/resources/footballscores/utils.py
qtile_extras/resources/github-icons/github.svg
qtile_extras/resources/global_menu/__init__.py
qtile_extras/resources/global_menu/registrar.py
qtile_extras/resources/media-icons/default.png
qtile_extras/resources/media-icons/default.svg
qtile_extras/resources/media-icons/next.svg
qtile_extras/resources/media-icons/play_pause.svg
qtile_extras/resources/media-icons/previous.svg
qtile_extras/resources/media-icons/stop.svg
qtile_extras/resources/snapcast/__init__.py
qtile_extras/resources/snapcast/snapcontrol.py
qtile_extras/resources/snapcast/snapmpris.py
qtile_extras/resources/snapcast-icons/snapcast.svg
qtile_extras/resources/stravadata/__init__.py
qtile_extras/resources/stravadata/locations.py
qtile_extras/resources/stravadata/sync.py
qtile_extras/resources/syncthing/syncthing.svg
qtile_extras-0.34.1.dist-info/licenses/LICENSE
qtile_extras-0.34.1.dist-info/METADATA
qtile_extras-0.34.1.dist-info/WHEEL
qtile_extras-0.34.1.dist-info/top_level.txt
qtile_extras-0.34.1.dist-info/RECORD
