Metadata-Version: 2.4
Name: qtile-extras
Version: 0.34.1
Summary: Extra items for qtile that are unlikely to be maintained in the main repo.
Author: elParaguayo
License-Expression: MIT
Project-URL: homepage, https://github.com/elParaguayo/qtile-extras
Project-URL: documentation, https://qtile-extras.readthedocs.io/en/stable/
Project-URL: changelog, https://qtile-extras.readthedocs.io/en/stable/changelog.html
Project-URL: issues, https://github.com/elParaguayo/qtile-extras/issues
Requires-Python: >=3.12
License-File: LICENSE
Provides-Extra: dev
Requires-Dist: coverage; extra == "dev"
Requires-Dist: coveralls; extra == "dev"
Requires-Dist: pytest-cov; extra == "dev"
Requires-Dist: pre-commit; extra == "dev"
Requires-Dist: PyGObject; extra == "dev"
Requires-Dist: isort; extra == "dev"
Requires-Dist: pytest<8.0.0; extra == "dev"
Requires-Dist: mypy; extra == "dev"
Requires-Dist: anyio; extra == "dev"
Requires-Dist: check-manifest; extra == "dev"
Requires-Dist: twine; extra == "dev"
Requires-Dist: build; extra == "dev"
Requires-Dist: pytest-rerunfailures; extra == "dev"
Requires-Dist: pytest-lazy-fixture; extra == "dev"
Requires-Dist: setuptools>=40.5.0; extra == "dev"
Requires-Dist: xkbcommon<1.1; extra == "dev"
Requires-Dist: pywayland==0.4.17; extra == "dev"
Requires-Dist: dbus-fast; extra == "dev"
Requires-Dist: xcffib>=1.4.0; extra == "dev"
Requires-Dist: cairocffi>=1.6.0; extra == "dev"
Requires-Dist: wheel; extra == "dev"
Provides-Extra: widgets
Requires-Dist: requests; extra == "widgets"
Requires-Dist: pint; extra == "widgets"
Requires-Dist: stravalib<=1.1.0; extra == "widgets"
Requires-Dist: iwlib; extra == "widgets"
Requires-Dist: psutil; extra == "widgets"
Requires-Dist: pulsectl-asyncio; extra == "widgets"
Dynamic: license-file
